lnd2dataframe/__init__.py
lnd2dataframe/client.py
lnd2dataframe-0.0.0.2.dist-info/LICENSE
lnd2dataframe-0.0.0.2.dist-info/METADATA
lnd2dataframe-0.0.0.2.dist-info/WHEEL
lnd2dataframe-0.0.0.2.dist-info/RECORD
